quoras/__init__.py
quoras/browser.py
quoras/quoras.py
quoras/scraper.py
quoras-1.1.1.dist-info/LICENSE
quoras-1.1.1.dist-info/METADATA
quoras-1.1.1.dist-info/WHEEL
quoras-1.1.1.dist-info/top_level.txt
quoras-1.1.1.dist-info/RECORD
